flumy/__init__.py
flumy/_flumy.so
flumy/version.py
flumy-8.500.dist-info/METADATA
flumy-8.500.dist-info/WHEEL
flumy-8.500.dist-info/top_level.txt
flumy-8.500.dist-info/RECORD
