Metadata-Version: 2.4
Name: flumy
Version: 8.500
Summary: Meandering Channelized Reservoir Creator
Author-email: Fabien Ors <fabien.ors@minesparis.psl.eu>
License: Proprietary
Project-URL: Homepage, https://flumy.minesparis.psl.eu
Project-URL: Issues, https://flumy.minesparis.psl.eu
Platform: Windows
Platform: Linux
Platform: Mac OS-X
Classifier: Programming Language :: Python :: 3
Classifier: Programming Language :: C++
Classifier: Development Status :: 4 - Beta
Classifier: Environment :: Other Environment
Classifier: Intended Audience :: Developers
Classifier: License :: Other/Proprietary License
Classifier: Operating System :: OS Independent
Classifier: Topic :: Software Development :: Libraries :: Python Modules
Requires-Python: >=3.8
Requires-Dist: numpy<3,>=1.24
Requires-Dist: matplotlib
Requires-Dist: scipy
Requires-Dist: plotly
Requires-Dist: pandas
